qermit/__init__.py
qermit/clifford_noise_characterisation/__init__.py
qermit/clifford_noise_characterisation/ccl.py
qermit/clifford_noise_characterisation/cdr_post.py
qermit/clifford_noise_characterisation/dfsc.py
qermit/coherent_pauli_checks/__init__.py
qermit/coherent_pauli_checks/box_clifford_subcircuits.py
qermit/coherent_pauli_checks/coherent_pauli_checks_mitres.py
qermit/coherent_pauli_checks/monochromatic_convex_subdag.py
qermit/coherent_pauli_checks/pauli_sampler.py
qermit/frame_randomisation/__init__.py
qermit/frame_randomisation/frame_randomisation.py
qermit/leakage_detection/__init__.py
qermit/leakage_detection/leakage_detection.py
qermit/noise_model/__init__.py
qermit/noise_model/mock_quantinuum_backend.py
qermit/noise_model/noise_model.py
qermit/noise_model/noisy_aer_backend.py
qermit/noise_model/pauli_error_transpile.py
qermit/noise_model/qermit_pauli.py
qermit/noise_model/transpiler_backend.py
qermit/postselection/__init__.py
qermit/postselection/postselect_manager.py
qermit/postselection/postselect_mitres.py
qermit/probabilistic_error_cancellation/__init__.py
qermit/probabilistic_error_cancellation/cliff_circuit_gen.py
qermit/probabilistic_error_cancellation/pec_learning_based.py
qermit/spam/__init__.py
qermit/spam/full_spam_correction.py
qermit/spam/full_transition_tomography.py
qermit/spam/spam_mitres.py
qermit/spectral_filtering/__init__.py
qermit/spectral_filtering/signal_filter.py
qermit/spectral_filtering/spectral_filtering.py
qermit/taskgraph/__init__.py
qermit/taskgraph/graphviz.py
qermit/taskgraph/measurement_reduction.py
qermit/taskgraph/mitex.py
qermit/taskgraph/mitres.py
qermit/taskgraph/mittask.py
qermit/taskgraph/task_graph.py
qermit/taskgraph/utils.py
qermit/zero_noise_extrapolation/__init__.py
qermit/zero_noise_extrapolation/zne.py
qermit-0.8.5.dist-info/METADATA
qermit-0.8.5.dist-info/WHEEL
qermit-0.8.5.dist-info/licenses/LICENSE
qermit-0.8.5.dist-info/RECORD
