Metadata-Version: 2.4
Name: qermit
Version: 0.8.5
Summary: Python package for quantum error mitigation.
License-File: LICENSE
Author: Daniel Mills
Author-email: daniel.mills@quantinuum.com
Requires-Python: >=3.10,<3.14
Classifier: Programming Language :: Python :: 3
Classifier: Programming Language :: Python :: 3.10
Classifier: Programming Language :: Python :: 3.11
Classifier: Programming Language :: Python :: 3.12
Classifier: Programming Language :: Python :: 3.13
Provides-Extra: docs
Provides-Extra: tests
Requires-Dist: furo (>=2024.8,<2025.10) ; extra == "docs"
Requires-Dist: jupyter-sphinx (>=0.5,<0.6) ; extra == "docs"
Requires-Dist: matplotlib (>=3.8,<3.11)
Requires-Dist: mypy (>=1.9,<1.19) ; extra == "tests"
Requires-Dist: myst-nb (>=1.1,<1.4) ; extra == "docs"
Requires-Dist: pytest (>=8.1,<9.1) ; extra == "tests"
Requires-Dist: pytest-cov (>=6.0,<7.1) ; extra == "tests"
Requires-Dist: pytket-qiskit (>=0.73,<0.74)
Requires-Dist: pytket-quantinuum[pecos] (>=0.41,<0.55)
Requires-Dist: qiskit-ibm-provider (>=0.11,<0.12) ; extra == "tests"
Requires-Dist: ruff (>=0.8,<0.15) ; extra == "tests"
Requires-Dist: sphinx (>=8.1,<8.3) ; extra == "docs"
Requires-Dist: sphinx-autodoc-typehints (>=2.5,<3.3) ; extra == "docs"
